MANIFEST.in
setup.py
version.txt
spiral_swarm.egg-info/PKG-INFO
spiral_swarm.egg-info/SOURCES.txt
spiral_swarm.egg-info/dependency_links.txt
spiral_swarm.egg-info/entry_points.txt
spiral_swarm.egg-info/requires.txt
spiral_swarm.egg-info/top_level.txt
spiralswarm/__init__.py
spiralswarm/__main__.py
spiralswarm/_version.py
spiralswarm/application.py
spiralswarm/interaction.py
spiralswarm/multicast.py
spiralswarm/transfer.py