Metadata-Version: 1.0
Name: spiral-swarm
Version: 0.14.0.0
Summary: easy local file transfer with curvecp
Home-page: UNKNOWN
Author: Aaron Gallagher
Author-email: _@habnab.it
License: UNKNOWN
Platform: UNKNOWN
